deepsea_commons/__init__.py
deepsea_commons/spark/__init__.py
deepsea_commons/spark/interface.py
deepsea_commons/spark/providers/__init__.py
deepsea_commons/spark/providers/pyspark/__init__.py
deepsea_commons/spark/providers/pyspark/main.py
deepsea_commons-0.0.1.dist-info/WHEEL
deepsea_commons-0.0.1.dist-info/METADATA
deepsea_commons-0.0.1.dist-info/RECORD
